.gitignore
.travis.yml
LICENSE
MANIFEST.in
README.md
setup.cfg
setup.py
omnibust/__init__.py
omnibust.egg-info/PKG-INFO
omnibust.egg-info/SOURCES.txt
omnibust.egg-info/dependency_links.txt
omnibust.egg-info/entry_points.txt
omnibust.egg-info/top_level.txt